hentai/__init__.py
hentai/hentai.py
hentai/data/__init__.py
hentai/data/tags.db
hentai-3.2.10.dist-info/LICENSE
hentai-3.2.10.dist-info/METADATA
hentai-3.2.10.dist-info/WHEEL
hentai-3.2.10.dist-info/entry_points.txt
hentai-3.2.10.dist-info/top_level.txt
hentai-3.2.10.dist-info/RECORD
