Metadata-Version: 2.1
Name: hentai
Version: 3.2.10
Summary: Implements a wrapper class around nhentai's RESTful API.
Home-page: https://www.hentai-chan.dev/projects/hentai
Author: hentai-chan
Author-email: dev.hentai-chan@outlook.com
License: General Public License V3
Project-URL: Documentation, https://www.hentai-chan.dev/projects/hentai
Project-URL: Source Code, https://github.com/hentai-chan/hentai
Project-URL: Bug Reports, https://github.com/hentai-chan/hentai/issues
Project-URL: Changelog, https://github.com/hentai-chan/hentai/blob/master/CHANGELOG.md
Keywords: hentai nhentai nhentai.net API NSFW
Platform: UNKNOWN
Classifier: Development Status :: 5 - Production/Stable
Classifier: License :: OSI Approved :: GNU General Public License v3 (GPLv3)
Classifier: Intended Audience :: Developers
Classifier: Natural Language :: English
Classifier: Programming Language :: Python :: 3.7
Classifier: Programming Language :: Python :: 3.8
Classifier: Programming Language :: Python :: 3.9
Classifier: Programming Language :: Python :: 3.10
Classifier: Operating System :: OS Independent
Classifier: Topic :: Education
Classifier: Topic :: Internet :: WWW/HTTP :: Dynamic Content
Classifier: Topic :: Software Development :: Libraries
Classifier: Topic :: Utilities
Requires-Python: >=3.7
Requires-Dist: tqdm (==4.63.0)
Requires-Dist: requests (==2.27.1)
